AUTHORS.txt
CHANGELOG.md
LICENSE.txt
MANIFEST.in
NEWS.md
README.md
requirements.txt
setup.py
anvio/__init__.py
anvio/auxiliarydataops.py
anvio/bamops.py
anvio/bottleroutes.py
anvio/ccollections.py
anvio/clustering.py
anvio/clusteringconfuguration.py
anvio/cogs.py
anvio/completeness.py
anvio/constants.py
anvio/contigops.py
anvio/db.py
anvio/dbops.py
anvio/dictio.py
anvio/errors.py
anvio/fastalib.py
anvio/filesnpaths.py
anvio/genecalling.py
anvio/genomedescriptions.py
anvio/genomesimilarity.py
anvio/genomestorage.py
anvio/hmmops.py
anvio/hmmopswrapper.py
anvio/homogeneityindex.py
anvio/interactive.py
anvio/kmers.py
anvio/learning.py
anvio/mcgclassifier.py
anvio/mcgops.py
anvio/merger.py
anvio/metapanops.py
anvio/panops.py
anvio/pfam.py
anvio/profiler.py
anvio/programs.py
anvio/samplesops.py
anvio/scgdomainclassifier.py
anvio/scgtaxonomyops.py
anvio/sequence.py
anvio/serverAPI.py
anvio/sge.py
anvio/splitter.py
anvio/structureops.py
anvio/summarizer.py
anvio/summaryhtml.py
anvio/synteny.py
anvio/terminal.py
anvio/ttycolors.py
anvio/utils.py
anvio/variability.py
anvio/variabilityops.py
anvio.egg-info/PKG-INFO
anvio.egg-info/SOURCES.txt
anvio.egg-info/dependency_links.txt
anvio.egg-info/requires.txt
anvio.egg-info/top_level.txt
anvio/data/__init__.py
anvio/data/SSMs/README.md
anvio/data/SSMs/__init__.py
anvio/data/SSMs/AA/BLOSUM62.txt
anvio/data/SSMs/AA/BLOSUM90.txt
anvio/data/SSMs/AA/__init__.py
anvio/data/SSMs/CDN/__init__.py
anvio/data/SSMs/NT/__init__.py
anvio/data/clusterconfigs/README.md
anvio/data/clusterconfigs/blank/tnf
anvio/data/clusterconfigs/blank/tnf-splits
anvio/data/clusterconfigs/merged/cov
anvio/data/clusterconfigs/merged/tnf
anvio/data/clusterconfigs/merged/tnf-cov
anvio/data/clusterconfigs/pan/frequency
anvio/data/clusterconfigs/pan/presence-absence
anvio/data/clusterconfigs/single/tnf
anvio/data/clusterconfigs/single/tnf-ab-cov
anvio/data/hmm/__init__.py
anvio/data/hmm/Archaea_76/genes.hmm.gz
anvio/data/hmm/Archaea_76/genes.txt
anvio/data/hmm/Archaea_76/kind.txt
anvio/data/hmm/Archaea_76/noise_cutoff_terms.txt
anvio/data/hmm/Archaea_76/reference.txt
anvio/data/hmm/Archaea_76/target.txt
