Metadata-Version: 1.1
Name: anvio
Version: 6.2
Summary: An interactive analysis and visualization platform for 'omics data. See https://merenlab.org/projects/anvio for more information
Home-page: https://merenlab.org/projects/anvio/
Author: anvi'o Authors
Author-email: a.murat.eren@gmail.com
License: GPLv3+
Keywords: metagenomics metatranscriptomics microbiology shotgun genomics MBL pipeline sequencing bam visualization SNP SNV
Platform: UNKNOWN
Classifier: Development Status :: 5 - Production/Stable
Classifier: Environment :: Console
Classifier: Environment :: Web Environment
Classifier: Intended Audience :: Science/Research
Classifier: License :: OSI Approved :: GNU General Public License v3 or later (GPLv3+)
Classifier: Natural Language :: English
Classifier: Operating System :: MacOS
Classifier: Operating System :: POSIX
Classifier: Programming Language :: Python :: 3 :: Only
Classifier: Programming Language :: JavaScript
Classifier: Programming Language :: C
Classifier: Topic :: Scientific/Engineering
